[
	{
		"年": 1914,
		"月": 11,
		"日": 1,
		"原文": "一日雨。星期休息。夜风。",
		"天气": [ "雨" ],
		"事件": [ "休息" ]
	},
    {
		"年":1914 ,
		"月":11 ,
		"日": 2,
		"原文":"二日雨。晨得二弟信，上月廿九日发。晚风。" ,
		"天气": ["雨" ],
		"事件": ["得信" ],
		"人物": ["二弟" ],
		"物件": ["信笺"]
	},
    {
		"年":1914 ,
		"月":11 ,
		"日":3 ,
		"原文":"三日晴，大风。午与张仲素、齐寿山、钱稻孙就小店饭。" ,
		"天气": ["晴"],
		"事件": ["餐饮" ],
		"人物": ["张仲素","齐寿山","钱稻孙" ]
	},
    {
		"年":1914 ,
		"月":11 ,
		"日":4 ,
		"原文":"四日晴，大冷有冰。上午寄二弟书一包：《丽楼丛书》七册，《唐人小说六种》二册，《三教{教}搜神大全》二册，《驴背集》二册，共十三册也。晚始持火炉入卧窟。陶书臣来。" ,
		"天气": ["晴" ],
		"事件": ["赠物" ],
		"人物": ["二弟" ],
		"物件": ["《丽楼丛书》","《唐人小说》"]
	},
    {
		"年":1914 ,
		"月":11 ,
		"日":5 ,
		"原文":"五日上午寄二弟信(七十一)，又《功顺堂丛书》一部二十四册，作一包。午后同齐寿山、常毅箴、黄芷涧游小市，买”大泉五十”两枚，“直百五铢”、“半两”各一枚，直一百五十文。" ,
		"事件": ["寄信","游小市" ],
		"人物": ["二弟", "齐寿山","常毅箴","黄芷涧"],
		"物件": ["《功顺堂丛书》"]
	},
    {
		"年":1914 ,
		"月":11 ,
		"日":6 ,
		"原文":"六日晴，大风。上午得二弟信，二日发(72)。午后同齐寿山、常毅箴游小市。乞桂百铸画山水一小帧。《之江日报》自送来。夜胃小痛。" ,
		"天气": ["晴" ],
		"事件": ["得信","游小市","胃痛" ],
		"人物": ["二弟","常毅箴","齐寿山" ],
		"物件": ["桂百铸画山水"]
	},
    {
		"年":1914 ,
		"月":11 ,
		"日":7 ,
		"原文":"七日晴。午后至小饭店午膳。同去者有齐寿山、许季上、钱稻孙，主人张仲素。下午同许季上往留黎厂买《复古编》一部三本，银八角。又《古学汇刊》第十编一部二册，银一元五分。" ,
		"天气": ["晴" ],
		"事件": ["午膳","订书" ],
		"人物": ["齐寿山","钱稻孙","张仲素","许季上" ],
		"物件": ["《复古编》","《古学汇刊》"],
		"地点": ["留黎厂"]
	},
    {
		"年":1914 ,
		"月":11 ,
		"日":8 ,
		"原文":"八日昙。星期休息。上午寄二弟信并刻书条例〔1〕一纸(七十二)。晚诗荃来借《化学》。" ,
		"天气": ["昙" ],
		"事件": ["寄信","借书" ],
		"人物": ["诗荃" ],
		"物件": ["《化学》"]
	},
    {
		"年":1914 ,
		"月":11 ,
		"日":9 ,
		"原文":"九日晴，风。午后与钱稻孙游小市。晚童亚镇来假去银三十元。" ,
		"天气": ["晴","风" ],
		"事件": ["游小市","借钱" ],
		"人物": ["童亚镇" ]
	},
    {
		"年":1914 ,
		"月":11 ,
		"日":10 ,
		"原文":"十日晴。上午寄二弟书籍二包，计《古学汇刊》第七至第十编八册共一包，《居士传》四册、《复古篇[编]》三册、《会稽郡故书杂集》草本〔2〕三册共一包。下午昙。晚宋紫佩来。夜雨雪。" ,
		"天气": ["晴" ],
		"事件": ["寄书" ],
		"人物": ["二弟","宋紫佩" ],
		"物件": ["《古学汇刊》","《居士传》","《复古篇》","《会稽郡故书杂集》"]
	},
    {
		"年":1914 ,
		"月":11 ,
		"日":11 ,
		"原文":"十一日昙。午后得二弟信，七日发(73)。又得陶念卿先生信，亦七日发。" ,
		"天气": ["昙" ],
		"事件": ["得信" ],
		"人物": ["二弟","淘念卿" ]
	},
    {
		"年":1914 ,
		"月":11 ,
		"日":12 ,
		"原文":"十二日昙。上午寄二弟信(七十三)，又书籍一包，计憨山《道德经注》二册，《庄子内篇注》二册，《天人感通录》一册，《会稽郡故书杂集》初稿三册。" ,
		"天气": ["昙" ],
		"事件": ["寄信" ],
		"人物": ["二弟","计憨山" ],
		"物件": ["《道德经注》","《庄子内篇注》","《天人感应录》","《会稽郡故书杂集》"]
	},
    {
		"年":1914 ,
		"月":11 ,
		"日":13 ,
		"原文":"十三日昙，午后晴。下午自部至许季上家小坐。得宋紫佩来信。" ,
		"天气": ["昙" ],
		"事件": ["小坐","得信" ],
		"人物": ["许季上","宋紫佩" ]
	},
    {
		"年":1914 ,
		"月":11 ,
		"日":14 ,
		"原文":"十四日晴，大风。午后往城南医院访毛漱泉。" ,
		"天气": ["晴" ],
		"事件": ["拜访" ],
		"人物": ["毛漱泉" ]
	},
    {
		"年":1914 ,
		"月":11 ,
		"日":15 ,
		"原文":"十五日晴。星期休息。下午往留黎厂，途遇季自求方来，因同往，至宝华堂买《说文校议》一部五册，《说文段注订补》一部八册，共价四元。归过南通馆坐少顷，持麻糕一包而归。夜得二弟信，十二日发(74)。" ,
		"天气": ["晴" ],
		"事件": ["休息" ],
		"人物": ["二弟" ],
		"物件": ["《说文校义》","《说文段注订补》","麻糕"],
		"地点": ["留黎厂","南通馆","宝华堂"]
	},
    {
		"年":1914 ,
		"月":11 ,
		"日":16 ,
		"原文":"十六日晴，午同齐寿山之市饭" ,
		"天气": ["晴" ],
		"事件": ["市饭" ],
		"人物": ["齐寿山" ]
	},
    {
		"年":1914 ,
		"月":11 ,
		"日":17 ,
		"原文":"十七日上午寄二弟信(七十四)。午后同常毅箴、黄芷涧之小市。夜雨。" ,
		"天气": ["夜雨" ],
		"事件": ["寄信" ],
		"人物": ["二弟","常毅箴","黄芷涧" ],
		"地点": ["小市"]
	},
    {
		"年":1914 ,
		"月":11 ,
		"日":18 ,
		"原文":"十八日晴。午后游小市。夜得二弟信，十五日发。" ,
		"天气": ["晴" ],
		"事件": ["游小市","得信" ],
		"人物": ["二弟" ],
		"物件": ["信笺"]
	},
    {
		"年":1914 ,
		"月":11 ,
		"日":19 ,
		"原文":"十九日昙，上午晴。午后同齐寿山之市饭。" ,
		"天气": ["昙" ],
		"事件": ["市饭" ],
		"人物": ["齐寿山" ]
	},
    {
		"年":1914 ,
		"月":11 ,
		"日":20 ,
		"原文":"二十日晴。午后之小市买古泉七枚，直铜元三十，有”端平折三”一枚佳。晚季市送肴一器。" ,
		"天气": ["晴" ],
		"事件": ["买物" ],
		"物件": ["古泉"],
		"地点": ["小市"]
	},
    {
		"年":1914 ,
		"月":11 ,
		"日":21 ,
		"原文":"二十一日晴。上午寄二弟信(七十五)。午后之小市。夜韩寿晋来假去二十元。" ,
		"天气": ["晴"],
		"事件": ["寄信","游小市" ],
		"人物": ["韩寿晋" ],
		"物件": ["二十元"]
	},
    {
		"年":1914 ,
		"月":11 ,
		"日":22 ,
		"原文":"二十二日晴。星期休息。上午得陈子英信，十八日发。午后刘立青来，捉令作画。季自求来。许季上来，借《阅藏知津》去。魏福绵来。晚至广和居餐，同坐有程伯高、许永康、季自求，而立青为主。" ,
		"天气": ["晴" ],
		"事件": ["休息","得信" ],
		"人物": ["陈子英","刘立青","程伯高","许永康","季自求" ],
		"物件": ["《阅藏知津》"]
	},
    {
		"年":1914 ,
		"月":11 ,
		"日":23 ,
		"原文":"二十三日晴，风。上午得二弟信并柳恽诗二叶，十九日发(76)。午后之小市，因大风地摊绝少。晚宋紫佩来。" ,
		"天气": ["晴" ],
		"事件": ["得信" ],
		"人物": ["二弟","宋紫佩" ],
		"物件": ["柳恽诗二叶"],
		"地点": ["小市"]
	},
    {
		"年":1914 ,
		"月":11 ,
		"日":24 ,
		"原文":"二十四日晴。无事。" ,
		"天气": ["晴" ],
		"事件": ["无事" ]
	},
    {
		"年":1914 ,
		"月":11 ,
		"日":25 ,
		"原文":"二十五日午后得羽太福子函，十六日发。夜许季市来。" ,
		"事件": ["得信" ],
		"人物": ["羽生福子","许季上" ],
		"物件": ["信函"]
	},
    {
		"年":1914 ,
		"月":11 ,
		"日":26 ,
		"原文":"二十六日昙。上午寄二弟信(七十六)。答陶念钦先生信。得二弟所寄书籍两束，计《小学答问》二部二册，《文史通义》一部六册，《慈闱琐记》一册，二十二日付邮。午后至东交民巷寄相摸屋书店信，代子英汇书款日金三十圆，需中银至四十元。下午得妇来书，二十二日从丁家弄朱宅发，颇谬。晚童亚镇来，言已汇款百元于家，因即付之，复除下前所借之三十元，与之七十。" ,
		"天气": ["昙" ],
		"事件": ["寄信","回信","得书","汇款" ],
		"人物": ["二弟" ,"陶念钦"],
		"物件": ["《小学答问》","《文史通义》","《慈闱琐记》"]
	},
    {
		"年":1914 ,
		"月":11 ,
		"日":27 ,
		"原文":"二十七日晴。上午得二弟信，二十三日发。夜译《儿童观念界之研究》讫。" ,
		"天气": ["晴" ],
		"事件": ["得信","翻译" ],
		"人物": ["二弟" ],
		"物件": ["《儿童观念界之研究》"]
	},
    {
		"年":1914 ,
		"月":11 ,
		"日":28 ,
		"原文":"二十八日昙。上午寄陈子英信。下午至有正局买汤注陶诗石印本一册，银二角。又封套一束，五分。晚魏福绵来取去银百元，云便令家汇与二弟也。夜毛漱泉来，赠以《炭画》一册。" ,
		"天气": ["昙" ],
		"事件": ["寄信","赠书" ],
		"人物": ["二弟","魏福棉","毛漱泉" ],
		"物件": ["汤注陶诗石印本","《炭画》"],
		"地点": ["有正局"]
	},
    {
		"年":1914 ,
		"月":11 ,
		"日":29 ,
		"原文":"二十九日昙。星期休息。午晴。午后往南通县馆访季自求，以《文史通义》赠之。至青云阁买牙粉一合，六角。至文明书局买仇十州绘文徵明书《飞燕外传》一册，一元六角。《黄瘿瓢人物册》一册，九角六分。夜风。" ,
		"天气": ["昙" ],
		"事件": ["休息","访友" ],
		"人物": ["季自求" ],
		"物件": ["《文史通义》","《飞燕外传》","《黄瘿瓢人物册》"]
	},
    {
		"年":1914 ,
		"月":11 ,
		"日":30 ,
		"原文":"三十日昙。上午得二弟明信片，云由童亚镇家汇款百元已到，二十六日发。夜微风。" ,
		"天气": ["昙" ],
		"事件": ["得信" ],
		"人物": ["二弟" ,"童亚镇"],
		"物件": ["明信片"]
	},
    {
		"年":1914 ,
		"月":12 ,
		"日":1 ,
		"原文":"一日晴，上午昙。寄二弟信(七十七)。午后风。晚季市来。" ,
		"天气": ["晴" ],
		"事件": ["寄信" ],
		"人物": ["季市" ],
		"物件": ["信件"]
	},
	{
		"年":1914 ,
		"月":12 ,
		"日":2 ,
		"原文":"二日晴。上午得二弟信，前月二十八日发。" ,
		"天气": ["晴" ],
		"事件": ["得信" ],
		"人物": ["二弟" ],
		"物件": ["信件"]
	},
	{
		"年":1914 ,
		"月":12 ,
		"日":3 ,
		"原文":"三日昙。上午收十一月俸银二百八十元。午后从王仲猷买得新华银行储蓄票一枚，价十元，第六十万二千四百七十五号。" ,
		"天气": ["昙" ],
		"事件": ["买储蓄票" ],
		"人物": ["王仲猷" ],
		"物件": ["储蓄票"]
	},
	{
		"年":1914 ,
		"月":12 ,
		"日":4 ,
		"原文":"四日晴。上午与季市函。" ,
		"天气": ["晴" ],
		"事件": ["写信" ],
		"人物": ["季市" ],
		"物件": ["信函"]
	},
	{
		"年":1914 ,
		"月":12 ,
		"日":5 ,
		"原文":"五日午后同常毅箴之小市，买古泉二枚，正书”唐国通宝”一枚，“洪化通宝”一枚，共五铜元。下午往流黎厂买《支那本大小乘论》残本七册，价二元。夜胃痛。" ,
		"天气": ["晴" ],
		"事件": ["游小市","买物" ],
		"人物": ["常毅箴" ],
		"物件": ["古泉","《支那本大小乘论》"],
		"地点": ["流黎厂"]
	},
	{
		"年":1914 ,
		"月":12 ,
		"日":6 ,
		"原文":"六日晴。星期休息。上午寄二弟信(七十八)。商契衡来。下午往留黎厂买南宋泉五枚”庆元折三”背”五”、“六”各一枚，“绍定折二”背”元”字一枚，“咸淳平泉”背”三”字一枚，又一价五角。又买《神州大观》第六集一册，一元七角五分；《三论玄义》一册，一角零四厘。夜服姜饮。得二弟信，三日发。风。" ,
		"天气": ["晴" ],
		"事件": ["休息","寄信","买物","得信" ],
		"人物": ["二弟" ],
		"物件": ["南宋泉"],
		"地点": ["留黎厂"]
	},
	{
		"年":1914 ,
		"月":12 ,
		"日":7 ,
		"原文":"七日晴，风。午后同齐寿山出饮加非。以支那本藏经”情”字二册赠许季上。寄商契衡信托借《类说》，不得。童亚镇来贻茗二合，假去二十元。晚子佩来。" ,
		"天气": ["晴" ],
		"事件": ["出饮","赠书" ],
		"人物": ["齐寿山","许季上","童亚镇" ,"子佩"],
		"物件": ["《类说》"]
	},
	{
		"年":1914 ,
		"月":12 ,
		"日":8 ,
		"原文":"八日上午寄朱逖先函。午后同齐寿山、戴螺舲、许季上至益錩饮加非。得相摸屋书店明信片，二日东京发。" ,
		"事件": ["寄信","饮酒" ],
		"人物": ["齐寿山","戴螺舲","许季上" ],
		"物件": ["明信片"],
		"地点": ["东京"]
	},
	{
		"年":1914 ,
		"月":12 ,
		"日":9 ,
		"原文":"九日晨至交民巷日邮局寄羽太家信，附与福子笺一枚，银二十五圆，内十五元为年末之用也。午后同夏司长往留黎厂买书，自买《楷帖四十种》一部四册，《续楷帖三十种》一部四册，分装两匣，价共十六元八角五分。" ,
		"事件": ["寄信","买书" ],
		"人物": ["羽生福子","夏司长" ],
		"物件": ["《楷帖四十种》","《续楷帖三十种》"],
		"地点": ["留黎厂"]
	},
	{
		"年":1914 ,
		"月":12 ,
		"日":10 ,
		"原文":"十日上午寄二弟信(七十九)。午后往留黎厂代部买书。陈师曾为作山水四小帧，又允为作花卉也。" ,
		"事件": ["寄信","买书" ],
		"人物": ["陈师" ],
		"物件": ["山水四小帧"],
		"地点": ["留黎厂"]
	},
	{
		"年":1914 ,
		"月":12 ,
		"日":11 ,
		"原文":"十一日昙。午后同齐寿山之小市。下午风。" ,
		"天气": ["昙" ],
		"事件": ["游小市" ],
		"人物": ["齐寿山" ],
		"地点": ["小市"]
	},
	{
		"年":1914 ,
		"月":12 ,
		"日":12 ,
		"原文":"十二日晴。上午得二弟信，附芳子信又书目二纸，八日发。午后邀仲素、寿山、芦舲、季上至益昌饭。得朱逖先信，本日发。晚访季市。商契衡来。" ,
		"天气": ["晴" ],
		"事件": ["得信" ],
		"人物": ["二弟","芳子","张仲素","戴螺舲" ],
		"物件": ["信纸"],
		"地点": ["留黎厂"]
	},
	{
		"年":1914 ,
		"月":12 ,
		"日":13,
		"原文":"十三日星期休息。午后季市来，又同至马幼渔寓，见君默、臤士、逖先、中季，晚归寓，还幼渔《四明六志》一部。夜宋紫佩来。季市来。服药治胃。" ,
		"事件": ["休息" ,"服药治胃"],
		"人物": ["季市" ],
		"物件": ["《四明六志》"],
		"地点": ["马幼渔寓"]
	},
	{
		"年":1914 ,
		"月":12 ,
		"日":14 ,
		"原文":"十二日昙，下午风。买益昌饼饵两种。" ,
		"天气": ["昙" ],
		"事件": ["买益昌饼饵" ],
		"物件": ["益昌饼饵"]
	},
	{
		"年":1914 ,
		"月":12 ,
		"日":15 ,
		"原文":"十五日晴。上午寄二弟信，附答芳子笺(八十)。送程伯高《小学答问》一册。下午风。晚季市送蒸鸭火腿一器。夜毛漱泉来。得陈子英信，十二日发。十二时顷小舅父自越中来，谭至二时顷。其行李在天津，借与被褥。" ,
		"天气": ["晴" ],
		"事件": ["寄信","送书" ],
		"人物": ["程伯高","季市","毛漱泉","陈子英" ],
		"物件": ["信函","蒸鸭火腿"],
		"地点": ["天津"]
	},
	{
		"年":1914 ,
		"月":12 ,
		"日":16 ,
		"原文":"十六日无事。夜大风。" ,
		"天气": ["风" ],
		"事件": ["无事" ]
	},
	{
		"年":1914 ,
		"月":12 ,
		"日":17,
		"原文":"十七日昙。上午得二弟信，十三日发。夜风一陈。" ,
		"天气": ["昙" ],
		"事件": ["得信" ],
		"人物": ["二弟" ],
		"物件": ["信笺"]
	},
	{
		"年":1914 ,
		"月":12 ,
		"日":18 ,
		"原文":"十八日晴。午后至同记理发。晚绕小市归。" ,
		"天气": ["晴" ],
		"事件": ["理发" ],
		"地点": ["小市","同记理发"]
	},
	{
		"年":1914 ,
		"月":12 ,
		"日":19 ,
		"原文":"十九日午同稻孙至益昌饭，又买饼饵一合，一元二角。午后同季市至劝业场。" ,
		"事件": ["买饭" ],
		"人物": ["钱稻孙","季市"],
		"物件": ["饼饵"],
		"地点": ["劝业场"]
	},
	{
		"年":1914 ,
		"月":12 ,
		"日":20 ,
		"原文":"二十日星期休息。上午寄二弟信(八十一)。午前许季上来谈。下午至留黎厂买《尔雅正义》一部十本，一元。又石印汉碑四种四册，一元二角五分。又买古竟一面，一元，四乳有四灵文。小舅父交来家托寄鱼干一合，又送牛肉两小合。" ,
		"事件": ["休息" ],
		"人物": ["二弟","许季上" ],
		"物件": ["信笺"],
		"地点": ["留黎厂"]
	},
	{
		"年":1914 ,
		"月":12 ,
		"日":21 ,
		"原文":"二十一日昙。午后与齐寿山至小市。夜风。得二弟信，十八日发(82)。" ,
		"天气": ["昙" ],
		"事件": ["游小市","得信" ],
		"人物": ["齐寿山","二弟" ],
		"物件": ["信笺"],
		"地点": ["小市"]
	},
	{
		"年":1914 ,
		"月":12 ,
		"日":22,
		"原文":"二十二日晨雪积半寸，上午霁。毛漱泉将返越，来别，假银二十元。午后同徐吉轩、许季上至通俗图书馆检阅小说。" ,
		"天气": ["雪天" ],
		"事件": ["借钱" ,"检阅小说"],
		"人物": ["毛漱泉" ],
		"物件": ["小说"],
		"地点": ["图书馆"]
	},
	{
		"年":1914 ,
		"月":12 ,
		"日":23 ,
		"原文":"二十三日冬至。休息。午后季市来，即同至马幼渔寓，晚归。伤风。" ,
		"事件": ["休息","伤风" ],
		"人物": ["马幼渔" ],
		"地点": ["马幼渔寓"]
	},
	{
		"年":1914 ,
		"月":12 ,
		"日":24,
		"原文":"二十四日晴。午后同齐寿山至小市。夜季市来。" ,
		"天气": ["晴" ],
		"事件": ["游小市" ],
		"人物": ["齐寿山","季市" ],
		"地点": ["小市"]
	},
	{
		"年":1914 ,
		"月":12 ,
		"日":25 ,
		"原文":"二十五日上午稻孙来，以《哀史》二册见借。寄二弟信(八十二)。同馆朱姓者尚无棉衣，赠五元，托陈仲篪转授。晚许诗荃来。夜风。" ,
		"事件": ["来访","寄信" ],
		"人物": ["钱稻孙","二弟","陈仲篪","许诗荃" ],
		"物件": ["棉衣"]
	},
	{
		"年":1914 ,
		"月":12 ,
		"日":26 ,
		"原文":"二十六日午后得二弟所寄印书格子纸十枚，十九日发。晚童亚镇、王镜清来。" ,
		"事件": ["得信" ],
		"人物": ["二弟","童亚镇","王镜清" ],
		"物件": ["书格子纸"]
	},
	{
		"年":1914 ,
		"月":12 ,
		"日":27 ,
		"原文":"二十七日晴，风。星期休息。午后至有正书局买《黄石斋夫人手书孝经》一册，三角；《明拓汉隶四种》、《刘熊碑》、《黄初修孔子庙碑》、《匋斋藏瘗鹤铭》、《水前拓本瘗鹤铭》各一册，共价二元五角五分。下午得二弟信，附三弟妇笺，二十三日发。得重久信，同日发。晚童亚镇来假去银三十元。" ,
		"天气": ["晴" ],
		"事件": ["休息" ],
		"人物": ["二弟" ],
		"物件": ["《黄石斋夫人手书孝经》","《明拓汉隶四种》","《刘熊碑》","《黄初修孔子庙碑》","《匋斋藏瘗鹤铭》","《水前拓本瘗鹤铭》"],
		"地点": ["有正书局"]
	},
	{
		"年":1914 ,
		"月":12 ,
		"日":28,
		"原文":"二十八日上午得本月俸二百八十元，托齐寿山存二百元，颁当差者八元。" ,
		"事件": ["发钱","存钱" ],
		"人物": ["齐寿山" ],
		"物件": ["月俸"]
	},
	{
		"年":1914 ,
		"月":12 ,
		"日":29 ,
		"原文":"二十九日昙。午后同齐寿山至益昌饭。" ,
		"天气": ["昙"],
		"事件": ["吃饭"],
		"人物": ["齐寿山" ],
		"地点": ["益昌"]
	},
	{
		"年":1914 ,
		"月":12 ,
		"日":30 ,
		"原文":"三十日昙。上午寄二弟信，附与芳子笺(八十三)。寄陈子英信。得羽太家信，二十日发。午后至留黎厂文明书局买《文衡山手书离骚》一册，又《诗稿》一册，《王觉斯自书诗》一册，《王良常楷书论书賸语》一册，《王梦楼自书快雨堂诗稿》一册，《沈石田移竹图》一册，共价银壹元四角二分五厘。又至有正书局买《张樗寮手书华严经墨迹》一册，叁角五分；《黄小松{所}藏汉碑五种》一部五册，一元二角。下午助湖北赈捐〔1〕二元，收观剧券一枚。买清秘阁纸八十枚，笔二支，价二元。晚舅父来谈，假去十元。季市来。夜风。" ,
		"天气": ["昙" ],
		"事件": ["寄信","买书","借钱" ],
		"人物": ["二弟","陈子英","季市","舅父" ],
		"物件": ["《黄石斋夫人手书孝经》","《明拓汉隶四种》","《刘熊碑》","《黄初修孔子庙碑》","《匋斋藏瘗鹤铭》"],
		"地点": ["清秘阁"]
	},
	{
		"年":1914,
		"月":12,
		"日":31,
		"原文":"三十一日晴。上午往马幼渔寓，见朱逖先、沈尹默、臤士、钱中季、汪旭初、吴[胡]仰曾、许季市，午饭后归。得陈师曾明信片。晚本部社会教育司同人公宴于西珠市口金谷春，同坐为徐吉轩、黄芷涧、许季上、戴芦盦、常毅箴、齐寿山、祁柏冈、林松坚、吴文瑄、王仲猷，共十一人。夜黄元生来。张协和送肴饵，受肴返饵。" ,
		"天气": ["晴" ],
		"事件": ["得陈师曾明信片" ],
		"人物": ["朱逖先","沈尹默","臤士","季自求" ],
		"物件": ["肴饵"],
		"地点": ["马幼渔寓","珠市口","金谷春"]
	}
]
