[
  {
    "name": "Alice",
    "age": 25,
    "gender": "female",
    "hobbies": ["reading", "swimming", "cooking"]
  },
  {
    "name": "Bob",
    "age": 30,
    "gender": "male",
    "hobbies": ["gaming", "cycling", "traveling"]
  },
  {
    "name": "Charlie",
    "age": 28,
    "gender": "male",
    "hobbies": ["music", "drawing", "writing"]
  },
  {
    "name": "Diana",
    "age": 32,
    "gender": "female",
    "hobbies": ["dancing", "singing", "yoga"]
  },
  {
    "name": "Eve",
    "age": 27,
    "gender": "female",
    "hobbies": ["shopping", "gardening", "knitting"]
  }
]
